duckframes/__init__.py
duckframes-0.0.5.dist-info/METADATA
duckframes-0.0.5.dist-info/WHEEL
duckframes-0.0.5.dist-info/licenses/LICENSE
duckframes-0.0.5.dist-info/RECORD
